__init__.py
__main__.py
app.py
cli.py
venv/bin/activate_this.py
venv/bin/rst2html.py
venv/bin/rst2html4.py
venv/bin/rst2html5.py
venv/bin/rst2latex.py
venv/bin/rst2man.py
venv/bin/rst2odt.py
venv/bin/rst2odt_prepstyles.py
venv/bin/rst2pseudoxml.py
venv/bin/rst2s5.py
venv/bin/rst2xetex.py
venv/bin/rst2xml.py
venv/bin/rstpep2html.py
venv/lib/python3.10/site-packages/_virtualenv.py
venv/lib/python3.10/site-packages/six.py
venv/lib/python3.10/site-packages/_distutils_hack/__init__.py
venv/lib/python3.10/site-packages/_distutils_hack/override.py
venv/lib/python3.10/site-packages/anytree/__init__.py
venv/lib/python3.10/site-packages/anytree/cachedsearch.py
venv/lib/python3.10/site-packages/anytree/dotexport.py
venv/lib/python3.10/site-packages/anytree/render.py
venv/lib/python3.10/site-packages/anytree/resolver.py
venv/lib/python3.10/site-packages/anytree/search.py
venv/lib/python3.10/site-packages/anytree/walker.py
venv/lib/python3.10/site-packages/anytree/exporter/__init__.py
venv/lib/python3.10/site-packages/anytree/exporter/dictexporter.py
venv/lib/python3.10/site-packages/anytree/exporter/dotexporter.py
venv/lib/python3.10/site-packages/anytree/exporter/jsonexporter.py
venv/lib/python3.10/site-packages/anytree/importer/__init__.py
venv/lib/python3.10/site-packages/anytree/importer/dictimporter.py
venv/lib/python3.10/site-packages/anytree/importer/jsonimporter.py
venv/lib/python3.10/site-packages/anytree/iterators/__init__.py
venv/lib/python3.10/site-packages/anytree/iterators/abstractiter.py
venv/lib/python3.10/site-packages/anytree/iterators/levelordergroupiter.py
venv/lib/python3.10/site-packages/anytree/iterators/levelorderiter.py
venv/lib/python3.10/site-packages/anytree/iterators/postorderiter.py
venv/lib/python3.10/site-packages/anytree/iterators/preorderiter.py
venv/lib/python3.10/site-packages/anytree/iterators/zigzaggroupiter.py
venv/lib/python3.10/site-packages/anytree/node/__init__.py
venv/lib/python3.10/site-packages/anytree/node/anynode.py
jenkinsdiagram-1.0.3.dist-info/METADATA
jenkinsdiagram-1.0.3.dist-info/WHEEL
jenkinsdiagram-1.0.3.dist-info/RECORD
