Metadata-Version: 2.1
Name: jenkinsdiagram
Version: 1.0.3
Summary: Generate mermaid diagrams from Jenkins pipelines
Project-URL: Homepage, https://github.com/IdiosApps/jenkinsdiagram
Project-URL: Bug Tracker, https://github.com/IdiosApps/jenkinsdiagram/issues
Author-email: James <IdiosApps@users.noreply.github.com>
Classifier: License :: OSI Approved :: MIT License
Classifier: Operating System :: OS Independent
Classifier: Programming Language :: Python :: 3
Requires-Python: >=3.11
Requires-Dist: anytree==2.8.0
Requires-Dist: click==8.1.3
Requires-Dist: colorama==0.4.6
Requires-Dist: commonmark==0.9.1
Requires-Dist: pygments==2.14.0
Requires-Dist: rich==12.6.0
Requires-Dist: shellingham==1.5.0.post1
Requires-Dist: six==1.16.0
Requires-Dist: typer==0.7.0
